setup.py
asyncd/__init__.py
asyncd/asyncd.py
asyncd.egg-info/PKG-INFO
asyncd.egg-info/SOURCES.txt
asyncd.egg-info/dependency_links.txt
asyncd.egg-info/not-zip-safe
asyncd.egg-info/requires.txt
asyncd.egg-info/top_level.txt