Metadata-Version: 1.0
Name: asyncd
Version: 1.37
Summary: Cool yet simple async for Python 3 and 2
Home-page: http://github.com/leungant/asyncd
Author: Anthony Leung
Author-email: anthony.leung@gmail.gm
License: MIT
Platform: UNKNOWN
